pypowsybl_jupyter/__init__.py
pypowsybl_jupyter/assets.py
pypowsybl_jupyter/nadexplorer.py
pypowsybl_jupyter/nadwidget.py
pypowsybl_jupyter/networkexplorer.py
pypowsybl_jupyter/networkmapwidget.py
pypowsybl_jupyter/selectcontext.py
pypowsybl_jupyter/sldwidget.py
pypowsybl_jupyter/util.py
pypowsybl_jupyter/static/nadwidget.css
pypowsybl_jupyter/static/nadwidget.js
pypowsybl_jupyter/static/networkmapwidget.css
pypowsybl_jupyter/static/networkmapwidget.js
pypowsybl_jupyter/static/nominal-voltage-filter.js
pypowsybl_jupyter/static/popupinfo.js
pypowsybl_jupyter/static/popupmenu.js
pypowsybl_jupyter/static/sldwidget.css
pypowsybl_jupyter/static/sldwidget.js
pypowsybl_jupyter/static/voltage-level-choice.js
pypowsybl_jupyter-1.3.0.dist-info/METADATA
pypowsybl_jupyter-1.3.0.dist-info/WHEEL
pypowsybl_jupyter-1.3.0.dist-info/licenses/LICENSE
pypowsybl_jupyter-1.3.0.dist-info/RECORD
