Metadata-Version: 2.4
Name: pypowsybl_jupyter
Version: 1.3.0
Summary: Widgets for pypowsybl in Jupyter notebooks
Project-URL: Homepage, https://github.com/powsybl/pypowsybl-jupyter
Author-email: Sylvain Leclerc <sylvain.leclerc@rte-france.com>, Christian Biasuzzi <christian.biasuzzi@soft.it>
License-Expression: MPL-2.0
License-File: LICENSE
Keywords: IPython,Jupyter,Widgets
Classifier: Framework :: Jupyter
Classifier: Intended Audience :: Developers
Classifier: Intended Audience :: Science/Research
Classifier: License :: OSI Approved :: Mozilla Public License 2.0 (MPL 2.0)
Classifier: Programming Language :: Python
Classifier: Programming Language :: Python :: 3
Classifier: Programming Language :: Python :: 3.8
Classifier: Programming Language :: Python :: 3.9
Classifier: Programming Language :: Python :: 3.10
Classifier: Programming Language :: Python :: 3.11
Classifier: Programming Language :: Python :: 3.12
Requires-Python: >=3.8
Requires-Dist: anywidget==0.9.18
Requires-Dist: pypowsybl>=1.13.0
Provides-Extra: dev
Requires-Dist: jupyterlab; extra == 'dev'
Requires-Dist: watchfiles; extra == 'dev'
